tlcpack_sphinx_addon/__init__.py
tlcpack_sphinx_addon/_static/css/gallery.css
tlcpack_sphinx_addon/_static/css/tlcpack_theme.css
tlcpack_sphinx_addon/_static/img/close-icon.svg
tlcpack_sphinx_addon/_static/img/downangle.svg
tlcpack_sphinx_addon/_static/img/dropdown-icon.svg
tlcpack_sphinx_addon/_static/img/dwonloaddoc.svg
tlcpack_sphinx_addon/_static/img/hide.svg
tlcpack_sphinx_addon/_static/img/menu-icon.svg
tlcpack_sphinx_addon/_static/img/nextarrow.svg
tlcpack_sphinx_addon/_static/img/note.svg
tlcpack_sphinx_addon/_static/img/pattern.svg
tlcpack_sphinx_addon/_static/img/prevarrow.svg
tlcpack_sphinx_addon/_static/img/right.svg
tlcpack_sphinx_addon/_static/img/rightangle.svg
tlcpack_sphinx_addon/_static/img/show.svg
tlcpack_sphinx_addon/_static/img/source.svg
tlcpack_sphinx_addon/_static/js/tlcpack_theme.js
tlcpack_sphinx_addon/_templates/breadcrumbs.html
tlcpack_sphinx_addon/_templates/footer.html
tlcpack_sphinx_addon/_templates/layout.html
tlcpack_sphinx_addon/_templates/themeheader.html
tlcpack_sphinx_addon-0.2.3.dist-info/LICENSE
tlcpack_sphinx_addon-0.2.3.dist-info/METADATA
tlcpack_sphinx_addon-0.2.3.dist-info/WHEEL
tlcpack_sphinx_addon-0.2.3.dist-info/top_level.txt
tlcpack_sphinx_addon-0.2.3.dist-info/RECORD
