Metadata-Version: 2.1
Name: tlcpack-sphinx-addon
Version: 0.2.3
Summary: TLCPack Sphinx addon
Home-page: https://github.com/tlc-pack/tlcpack-sphinx-addon
Author: tlcpack
Author-email: tianqi.tchen@gmail.com
License: Apache-2.0
Classifier: Development Status :: 3 - Alpha
Classifier: Intended Audience :: Developers
Classifier: Topic :: Software Development :: Build Tools
Classifier: License :: OSI Approved :: Apache Software License
Classifier: Programming Language :: Python :: 3
Classifier: Programming Language :: Python :: 3.6
License-File: LICENSE
